tinkoff_voicekit_ai/__init__.py
tinkoff_voicekit_ai/Operations/__init__.py
tinkoff_voicekit_ai/Operations/aio_long_running.py
tinkoff_voicekit_ai/Operations/config_schema.py
tinkoff_voicekit_ai/Operations/helper_operations.py
tinkoff_voicekit_ai/Operations/long_running.py
tinkoff_voicekit_ai/Operations/__pycache__/__init__.cpython-312.pyc
tinkoff_voicekit_ai/Operations/__pycache__/aio_long_running.cpython-312.pyc
tinkoff_voicekit_ai/Operations/__pycache__/config_schema.cpython-312.pyc
tinkoff_voicekit_ai/Operations/__pycache__/helper_operations.cpython-312.pyc
tinkoff_voicekit_ai/Operations/__pycache__/long_running.cpython-312.pyc
tinkoff_voicekit_ai/STT/__init__.py
tinkoff_voicekit_ai/STT/aio_client_stt.py
tinkoff_voicekit_ai/STT/client_stt.py
tinkoff_voicekit_ai/STT/config_schema.py
tinkoff_voicekit_ai/STT/helper_stt.py
tinkoff_voicekit_ai/STT/__pycache__/__init__.cpython-312.pyc
tinkoff_voicekit_ai/STT/__pycache__/aio_client_stt.cpython-312.pyc
tinkoff_voicekit_ai/STT/__pycache__/client_stt.cpython-312.pyc
tinkoff_voicekit_ai/STT/__pycache__/config_schema.cpython-312.pyc
tinkoff_voicekit_ai/STT/__pycache__/helper_stt.cpython-312.pyc
tinkoff_voicekit_ai/TTS/__init__.py
tinkoff_voicekit_ai/TTS/aio_client_tts.py
tinkoff_voicekit_ai/TTS/client_tts.py
tinkoff_voicekit_ai/TTS/config_schema.py
tinkoff_voicekit_ai/TTS/configurator_codec.py
tinkoff_voicekit_ai/TTS/helper_tts.py
tinkoff_voicekit_ai/TTS/__pycache__/__init__.cpython-312.pyc
tinkoff_voicekit_ai/TTS/__pycache__/aio_client_tts.cpython-312.pyc
tinkoff_voicekit_ai/TTS/__pycache__/client_tts.cpython-312.pyc
tinkoff_voicekit_ai/TTS/__pycache__/config_schema.cpython-312.pyc
tinkoff_voicekit_ai/TTS/__pycache__/configurator_codec.cpython-312.pyc
tinkoff_voicekit_ai/TTS/__pycache__/helper_tts.cpython-312.pyc
tinkoff_voicekit_ai/TTS/opuslibwin/libeay32.dll
tinkoff_voicekit_ai/TTS/opuslibwin/libgcc_s_sjlj-1.dll
tinkoff_voicekit_ai/TTS/opuslibwin/libogg-0.dll
tinkoff_voicekit_ai/TTS/opuslibwin/libopusfile-0.dll
tinkoff_voicekit_ai-0.3.3.post1.dist-info/METADATA
tinkoff_voicekit_ai-0.3.3.post1.dist-info/WHEEL
tinkoff_voicekit_ai-0.3.3.post1.dist-info/top_level.txt
tinkoff_voicekit_ai-0.3.3.post1.dist-info/RECORD
