Metadata-Version: 2.2
Name: tinkoff_voicekit_ai
Version: 0.3.3.post1
Summary: Python Tinkoff Speech API
Home-page: https://github.com/Cornil79/tinkoff_voicekit_ai
Author: Albert Toma & Tinkoff Speech Team
Author-email: Albert Toma & Tinkoff Speech Team <cornil@mail.ru>
License: Apache-2.0
Classifier: Programming Language :: Python :: 3
Classifier: License :: OSI Approved :: Apache Software License
Classifier: Operating System :: OS Independent
Requires-Python: >=3.6
Requires-Dist: boto3>=1.28.0
Requires-Dist: aioboto3>=11.0.0
Requires-Dist: google>=3.0.0
Requires-Dist: jsonschema>=4.0.0
Requires-Dist: opuslib==3.0.1
Requires-Dist: grpcio>=1.50.0
Requires-Dist: grpcio-tools>=1.50.0
Requires-Dist: googleapis-common-protos>=1.60.0
Requires-Dist: requests>=2.31.0
Requires-Dist: pytest-asyncio>=0.21.0
Requires-Dist: pytest>=7.0.0
Requires-Dist: protobuf==4.25.5
Provides-Extra: testing
Requires-Dist: pytest; extra == "testing"
Dynamic: author
